hefeng_weather/__init__.py
hefeng_weather/cli.py
hefeng_weather/core.py
hefeng_weather-0.1.5.dist-info/METADATA
hefeng_weather-0.1.5.dist-info/WHEEL
hefeng_weather-0.1.5.dist-info/entry_points.txt
hefeng_weather-0.1.5.dist-info/top_level.txt
hefeng_weather-0.1.5.dist-info/RECORD
