Metadata-Version: 2.4
Name: hefeng-weather
Version: 0.1.5
Summary: hefeng-weather mcp
Requires-Python: >=3.10
Requires-Dist: mcp[cli]>=1.6.0
Requires-Dist: requests>=2.32.3
